diff --git a/mods/ngtlib.deobf.jar.src.processed/jp/ngt/ngtlib/command/CommandPermit.jasm b/src/main/ngtlib/jp/ngt/ngtlib/command/CommandPermit.jasm
index 89cf20c..bb3eb7d 100644
--- a/mods/ngtlib.deobf.jar.src.processed/jp/ngt/ngtlib/command/CommandPermit.jasm
+++ b/src/main/ngtlib/jp/ngt/ngtlib/command/CommandPermit.jasm
@@ -42,56 +42,57 @@ L_0004:
     .limit local 2
 L_0000:
     .line 29
     .var 0 is this Ljp/ngt/ngtlib/command/CommandPermit; from L_0000 to L_0004
     .var 1 is sender Lnet/minecraft/command/ICommandSender; from L_0000 to L_0004
     ldc "commands.permit.usage"
     areturn
 L_0004:
 .end method
 
+.method private static getPlayerOrNull "(Lnet/minecraft/command/ICommandSender;)Lnet/minecraft/entity/player/EntityPlayerMP;"
+    .limit stack 1
+    .limit local 1
+    .catch net/minecraft/command/PlayerNotFoundException from L_start to L_catch using L_catch
+
+L_start:
+    .line 1038
+    .var 0 is sender Lnet/minecraft/command/ICommandSender; from L_start to L_end
+    aload 0
+    invokestatic jp/ngt/ngtlib/command/CommandPermit/getCommandSenderAsPlayer (Lnet/minecraft/command/ICommandSender;)Lnet/minecraft/entity/player/EntityPlayerMP;
+    areturn
+L_catch:
+    .line 1042
+    .stack
+        locals Object net/minecraft/command/ICommandSender
+        stacks Object net/minecraft/command/PlayerNotFoundException
+    .end stack
+    pop
+    aconst_null
+    areturn
+L_end:
+
+.end method
+
 .method public execute "(Lnet/minecraft/server/MinecraftServer;Lnet/minecraft/command/ICommandSender;[Ljava/lang/String;)V"
     .throws net/minecraft/command/CommandException
     .limit stack 4
     .limit local 7
-    .catch net/minecraft/command/PlayerNotFoundException from L_0000 to L_0005 using L_0008
 L_0000:
-    .line 38
+    .line 43
     .var 0 is this Ljp/ngt/ngtlib/command/CommandPermit; from L_0000 to L_009c
     .var 1 is server Lnet/minecraft/server/MinecraftServer; from L_0000 to L_009c
     .var 2 is sender Lnet/minecraft/command/ICommandSender; from L_0000 to L_009c
     .var 3 is args "[Ljava/lang/String;" from L_0000 to L_009c
-    aload 2
-    invokestatic jp/ngt/ngtlib/command/CommandPermit/getCommandSenderAsPlayer (Lnet/minecraft/command/ICommandSender;)Lnet/minecraft/entity/player/EntityPlayerMP;
+    aconst_null
     astore 4
-L_0005:
-    .line 44
-    .var 4 is player Lnet/minecraft/entity/player/EntityPlayerMP; from L_0005 to L_0008
-    goto L_0013
-L_0008:
-    .line 40
-    .stack
-        locals Object jp/ngt/ngtlib/command/CommandPermit
-        locals Object net/minecraft/server/MinecraftServer
-        locals Object net/minecraft/command/ICommandSender
-        locals Object "[Ljava/lang/String;"
-        stacks Object net/minecraft/command/PlayerNotFoundException
-    .end stack
-    astore 5
-L_000c:
-    .line 42
-    .var 5 is e Lnet/minecraft/command/PlayerNotFoundException; from L_000c to L_0013
-    aload 5
-    invokevirtual net/minecraft/command/PlayerNotFoundException/printStackTrace ()V
-L_0010:
-    .line 43
-    return
+
 L_0013:
     .line 46
     .var 4 is player Lnet/minecraft/entity/player/EntityPlayerMP; from L_0013 to L_009c
     .stack
         locals Object jp/ngt/ngtlib/command/CommandPermit
         locals Object net/minecraft/server/MinecraftServer
         locals Object net/minecraft/command/ICommandSender
         locals Object "[Ljava/lang/String;"
         locals Object net/minecraft/entity/player/EntityPlayerMP
     .end stack
@@ -102,44 +103,46 @@ L_0019:
     .line 48
     aload 3
     iconst_0
     aaload
     ldc "list"
     invokevirtual java/lang/String/equals (Ljava/lang/Object;)Z
     ifeq L_0029
 L_0021:
     .line 50
     getstatic jp/ngt/ngtlib/util/PermissionManager/INSTANCE Ljp/ngt/ngtlib/util/PermissionManager;
-    aload 4
+    aload 2
+    invokestatic jp/ngt/ngtlib/command/CommandPermit/getCommandSenderAsPlayer (Lnet/minecraft/command/ICommandSender;)Lnet/minecraft/entity/player/EntityPlayerMP;
     invokevirtual jp/ngt/ngtlib/util/PermissionManager/showPermissionList (Lnet/minecraft/entity/player/EntityPlayer;)V
 L_0026:
     .line 51
     return
 L_0029:
     .line 53
     .stack use locals
     .end stack
     aload 3
     iconst_0
     aaload
     ldc "myname"
     invokevirtual java/lang/String/equals (Ljava/lang/Object;)Z
     ifeq L_0044
 L_0032:
     .line 55
-    aload 4
+    aload 2
     new java/lang/StringBuilder
     dup
     invokespecial java/lang/StringBuilder/<init> ()V
     ldc "My name is "
     invokevirtual java/lang/StringBuilder/append (Ljava/lang/String;)Ljava/lang/StringBuilder;
-    aload 4
+    aload 2
+    invokestatic jp/ngt/ngtlib/command/CommandPermit/getCommandSenderAsPlayer (Lnet/minecraft/command/ICommandSender;)Lnet/minecraft/entity/player/EntityPlayerMP;
     invokevirtual net/minecraft/entity/player/EntityPlayerMP/getName ()Ljava/lang/String;
     invokevirtual java/lang/StringBuilder/append (Ljava/lang/String;)Ljava/lang/StringBuilder;
     invokevirtual java/lang/StringBuilder/toString ()Ljava/lang/String;
     iconst_0
     anewarray java/lang/Object
     invokestatic jp/ngt/ngtlib/io/NGTLog/sendChatMessage "(Lnet/minecraft/command/ICommandSender;Ljava/lang/String;[Ljava/lang/Object;)V"
 L_0041:
     .line 56
     return
 L_0044:
@@ -168,21 +171,22 @@ L_0057:
     .var 6 is target Ljava/lang/String; from L_0057 to L_007c
     aload 3
     iconst_0
     aaload
     ldc "add"
     invokevirtual java/lang/String/equals (Ljava/lang/Object;)Z
     ifeq L_0069
 L_005f:
     .line 65
     getstatic jp/ngt/ngtlib/util/PermissionManager/INSTANCE Ljp/ngt/ngtlib/util/PermissionManager;
-    aload 4
+    aload 2
+    invokestatic jp/ngt/ngtlib/command/CommandPermit/getPlayerOrNull (Lnet/minecraft/command/ICommandSender;)Lnet/minecraft/entity/player/EntityPlayerMP;
     aload 5
     aload 6
     invokevirtual jp/ngt/ngtlib/util/PermissionManager/addPermission (Lnet/minecraft/entity/player/EntityPlayer;Ljava/lang/String;Ljava/lang/String;)V
 L_0066:
     .line 66
     return
 L_0069:
     .line 68
     .stack
         locals Object jp/ngt/ngtlib/command/CommandPermit
@@ -195,58 +199,59 @@ L_0069:
     .end stack
     aload 3
     iconst_0
     aaload
     ldc "remove"
     invokevirtual java/lang/String/equals (Ljava/lang/Object;)Z
     ifeq L_007c
 L_0072:
     .line 70
     getstatic jp/ngt/ngtlib/util/PermissionManager/INSTANCE Ljp/ngt/ngtlib/util/PermissionManager;
-    aload 4
+    aload 2
+    invokestatic jp/ngt/ngtlib/command/CommandPermit/getPlayerOrNull (Lnet/minecraft/command/ICommandSender;)Lnet/minecraft/entity/player/EntityPlayerMP;
     aload 5
     aload 6
     invokevirtual jp/ngt/ngtlib/util/PermissionManager/removePermission (Lnet/minecraft/entity/player/EntityPlayer;Ljava/lang/String;Ljava/lang/String;)V
 L_0079:
     .line 71
     return
 L_007c:
     .line 76
     .stack
         locals Object jp/ngt/ngtlib/command/CommandPermit
         locals Object net/minecraft/server/MinecraftServer
         locals Object net/minecraft/command/ICommandSender
         locals Object "[Ljava/lang/String;"
         locals Object net/minecraft/entity/player/EntityPlayerMP
     .end stack
-    aload 4
+    aload 2
     ldc "/permit add <player> <category>"
     iconst_0
     anewarray java/lang/Object
     invokestatic jp/ngt/ngtlib/io/NGTLog/sendChatMessage "(Lnet/minecraft/command/ICommandSender;Ljava/lang/String;[Ljava/lang/Object;)V"
 L_0084:
     .line 77
-    aload 4
+    aload 2
     ldc "/permit remove <player> <category>"
     iconst_0
     anewarray java/lang/Object
     invokestatic jp/ngt/ngtlib/io/NGTLog/sendChatMessage "(Lnet/minecraft/command/ICommandSender;Ljava/lang/String;[Ljava/lang/Object;)V"
 L_008b:
     .line 78
-    aload 4
+    aload 2
     ldc "/permit list"
     iconst_0
     anewarray java/lang/Object
     invokestatic jp/ngt/ngtlib/io/NGTLog/sendChatMessage "(Lnet/minecraft/command/ICommandSender;Ljava/lang/String;[Ljava/lang/Object;)V"
 L_0092:
     .line 79
-    aload 4
+    aload 2
     ldc "/permit myname"
     iconst_0
     anewarray java/lang/Object
     invokestatic jp/ngt/ngtlib/io/NGTLog/sendChatMessage "(Lnet/minecraft/command/ICommandSender;Ljava/lang/String;[Ljava/lang/Object;)V"
 L_0099:
     .line 80
     return
 L_009c:
 .end method
 
diff --git a/mods/ngtlib.deobf.jar.src.processed/jp/ngt/ngtlib/io/NGTLog.jasm b/src/main/ngtlib/jp/ngt/ngtlib/io/NGTLog.jasm
index ea31691..427b9b6 100644
--- a/mods/ngtlib.deobf.jar.src.processed/jp/ngt/ngtlib/io/NGTLog.jasm
+++ b/src/main/ngtlib/jp/ngt/ngtlib/io/NGTLog.jasm
@@ -1,16 +1,16 @@
 .bytecode 52.0
 .source "NGTLog.java"
 .class public final jp/ngt/ngtlib/io/NGTLog
 .super java/lang/Object
 
-.field private static final logger Lorg/apache/logging/log4j/Logger;
+.field public static final logger Lorg/apache/logging/log4j/Logger;
 .end field
 
 .field private static final startTimes Ljava/util/List;
     .signature "Ljava/util/List<Ljava/lang/Long;>;"
 .end field
 
 .method public <init> ()V
     .limit stack 1
     .limit local 1
 L_0000:
@@ -32,65 +32,90 @@ L_0000:
     iconst_0
     anewarray java/lang/Object
     invokestatic jp/ngt/ngtlib/io/NGTLog/debug "(Ljava/lang/String;[Ljava/lang/Object;)V"
 L_0006:
     .line 26
     return
 L_0009:
 .end method
 
 .method public static varargs debug "(Ljava/lang/String;[Ljava/lang/Object;)V"
+    .limit stack 3
+    .limit local 3
+    aload 0
+    aload 1
+    getstatic org/apache/logging/log4j/Level/INFO Lorg/apache/logging/log4j/Level;
+    invokestatic jp/ngt/ngtlib/io/NGTLog/_log_ "(Ljava/lang/String;[Ljava/lang/Object;Lorg/apache/logging/log4j/Level;)V"
+    return
+L_0023:
+.end method
+
+.method public static varargs trace "(Ljava/lang/String;[Ljava/lang/Object;)V"
+    .limit stack 3
+    .limit local 3
+    aload 0
+    aload 1
+    getstatic org/apache/logging/log4j/Level/TRACE Lorg/apache/logging/log4j/Level;
+    invokestatic jp/ngt/ngtlib/io/NGTLog/_log_ "(Ljava/lang/String;[Ljava/lang/Object;Lorg/apache/logging/log4j/Level;)V"
+    return
+L_0023:
+.end method
+
+.method public static _log_ "(Ljava/lang/String;[Ljava/lang/Object;Lorg/apache/logging/log4j/Level;)V"
     .limit stack 3
     .limit local 3
     .catch java/lang/Exception from L_0000 to L_0018 using L_001b
 L_0000:
     .line 32
     .var 0 is par1 Ljava/lang/String; from L_0000 to L_0023
     .var 1 is par2 "[Ljava/lang/Object;" from L_0000 to L_0023
+    .var 2 is label "Lorg/apache/logging/log4j/Level;" from L_0000 to L_0023
     aload 0
-    astore 2
+    astore 3
 L_0004:
     .line 33
-    .var 2 is message Ljava/lang/String; from L_0004 to L_0018
+    .var 3 is message Ljava/lang/String; from L_0004 to L_0018
     aload 1
     ifnull L_0011
     aload 1
     arraylength
     ifle L_0011
 L_000b:
     .line 35
     aload 0
     aload 1
     invokestatic java/lang/String/format "(Ljava/lang/String;[Ljava/lang/Object;)Ljava/lang/String;"
-    astore 2
+    astore 3
 L_0011:
     .line 37
     .stack
         locals Object java/lang/String
         locals Object "[Ljava/lang/Object;"
+        locals Object org/apache/logging/log4j/Level
         locals Object java/lang/String
     .end stack
     getstatic jp/ngt/ngtlib/io/NGTLog/logger Lorg/apache/logging/log4j/Logger;
-    getstatic org/apache/logging/log4j/Level/INFO Lorg/apache/logging/log4j/Level;
     aload 2
+    aload 3
     invokeinterface org/apache/logging/log4j/Logger/log (Lorg/apache/logging/log4j/Level;Ljava/lang/String;)V
 L_0018:
     .line 42
     goto L_001f
 L_001b:
     .line 39
     .stack
         locals Object java/lang/String
         locals Object "[Ljava/lang/Object;"
+        locals Object org/apache/logging/log4j/Level
         stacks Object java/lang/Exception
     .end stack
-    astore 2
+    pop
 L_001f:
     .line 43
     .stack use locals
     .end stack
     return
 L_0023:
 .end method
 
 .method public static varargs sendChatMessage "(Lnet/minecraft/command/ICommandSender;Ljava/lang/String;[Ljava/lang/Object;)V"
     .limit stack 5
diff --git a/mods/ngtlib.deobf.jar.src.processed/jp/ngt/ngtlib/renderer/model/ModelLoader.jasm b/src/main/ngtlib/jp/ngt/ngtlib/renderer/model/ModelLoader.jasm
index a2f9d39..27e8e57 100644
--- a/mods/ngtlib.deobf.jar.src.processed/jp/ngt/ngtlib/renderer/model/ModelLoader.jasm
+++ b/src/main/ngtlib/jp/ngt/ngtlib/renderer/model/ModelLoader.jasm
@@ -33,20 +33,36 @@ L_0000:
     aload 0
     invokespecial jp/ngt/ngtlib/io/ResourceLocationCustom/<init> (Ljava/lang/String;Ljava/lang/String;)V
     aload 1
     aload 2
     invokestatic jp/ngt/ngtlib/renderer/model/ModelLoader/loadModel "(Lnet/minecraft/util/ResourceLocation;Ljp/ngt/ngtlib/renderer/model/VecAccuracy;[Ljava/lang/Object;)Ljp/ngt/ngtlib/renderer/model/PolygonModel;"
     areturn
 L_000b:
 .end method
 
 .method public static varargs loadModel "(Lnet/minecraft/util/ResourceLocation;Ljp/ngt/ngtlib/renderer/model/VecAccuracy;[Ljava/lang/Object;)Ljp/ngt/ngtlib/renderer/model/PolygonModel;"
+    .limit stack 3
+    .limit local 3
+L_begin:
+    .line 29
+    .var 0 is resource Lnet/minecraft/util/ResourceLocation; from L_begin to L_end
+    .var 1 is par1 Ljp/ngt/ngtlib/renderer/model/VecAccuracy; from L_begin to L_end
+    .var 2 is args "[Ljava/lang/Object;" from L_begin to L_end
+    aload 0
+    aload 1
+    aload 2
+    invokestatic com/anatawa12/fixRtm/ngtlib/renderer/model/ModelLoaderKt/loadModel "(Lnet/minecraft/util/ResourceLocation;Ljp/ngt/ngtlib/renderer/model/VecAccuracy;[Ljava/lang/Object;)Ljp/ngt/ngtlib/renderer/model/PolygonModel;"
+    areturn
+L_end:
+.end method
+
+.method public static varargs loadModel__NGTLIB "(Lnet/minecraft/util/ResourceLocation;Ljp/ngt/ngtlib/renderer/model/VecAccuracy;[Ljava/lang/Object;)Ljp/ngt/ngtlib/renderer/model/PolygonModel;"
     .limit stack 4
     .limit local 9
     .catch java/io/IOException from L_0026 to L_002b using L_002e
     .catch java/io/IOException from L_0005 to L_0043 using L_0054
     .catch java/io/IOException from L_0045 to L_0052 using L_0054
 L_0000:
     .line 29
     .var 0 is resource Lnet/minecraft/util/ResourceLocation; from L_0000 to L_0067
     .var 1 is par1 Ljp/ngt/ngtlib/renderer/model/VecAccuracy; from L_0000 to L_0067
     .var 2 is args "[Ljava/lang/Object;" from L_0000 to L_0067
diff --git a/mods/ngtlib.deobf.jar.src.processed/jp/ngt/ngtlib/renderer/model/ObjModel.jasm b/src/main/ngtlib/jp/ngt/ngtlib/renderer/model/ObjModel.jasm
index 9c7d247..1840c0a 100644
--- a/mods/ngtlib.deobf.jar.src.processed/jp/ngt/ngtlib/renderer/model/ObjModel.jasm
+++ b/src/main/ngtlib/jp/ngt/ngtlib/renderer/model/ObjModel.jasm
@@ -1532,31 +1532,20 @@ L_0007:
     .limit stack 1
     .limit local 1
 L_0000:
     .line 422
     .var 0 is this Ljp/ngt/ngtlib/renderer/model/ObjModel; from L_0000 to L_0004
     getstatic jp/ngt/ngtlib/io/FileType/OBJ Ljp/ngt/ngtlib/io/FileType;
     areturn
 L_0004:
 .end method
 
-.method public getDrawMode ()I
-    .limit stack 1
-    .limit local 1
-L_0000:
-    .line 428
-    .var 0 is this Ljp/ngt/ngtlib/renderer/model/ObjModel; from L_0000 to L_0004
-    iconst_4
-    ireturn
-L_0004:
-.end method
-
 .method public getMaterials ()Ljava/util/Map;
     .signature "()Ljava/util/Map<Ljava/lang/String;Ljp/ngt/ngtlib/renderer/model/Material;>;"
     .limit stack 1
     .limit local 1
 L_0000:
     .line 434
     .var 0 is this Ljp/ngt/ngtlib/renderer/model/ObjModel; from L_0000 to L_0005
     aload 0
     getfield jp/ngt/ngtlib/renderer/model/ObjModel/materials Ljava/util/Map;
     areturn
diff --git a/mods/ngtlib.deobf.jar.src.processed/jp/ngt/ngtlib/renderer/model/PolygonModel.jasm b/src/main/ngtlib/jp/ngt/ngtlib/renderer/model/PolygonModel.jasm
index 5d26e9d..84909bf 100644
--- a/mods/ngtlib.deobf.jar.src.processed/jp/ngt/ngtlib/renderer/model/PolygonModel.jasm
+++ b/src/main/ngtlib/jp/ngt/ngtlib/renderer/model/PolygonModel.jasm
@@ -8,21 +8,21 @@
 .annotation visible net/minecraftforge/fml/relauncher/SideOnly
     value e = net/minecraftforge/fml/relauncher/Side CLIENT
 .end annotation
 
 .field protected fileName Ljava/lang/String;
 .end field
 
 .field protected drawMode I
 .end field
 
-.field protected accuracy Ljp/ngt/ngtlib/renderer/model/VecAccuracy;
+.field public accuracy Ljp/ngt/ngtlib/renderer/model/VecAccuracy;
 .end field
 
 .field protected sizeBox "[F"
 .end field
 
 .field public final vertices Ljava/util/List;
     .signature "Ljava/util/List<Ljp/ngt/ngtlib/renderer/model/Vertex;>;"
 .end field
 
 .field public final groupObjects Ljava/util/List;
@@ -480,21 +480,21 @@ L_0078:
     .limit local 1
 L_0000:
     .line 152
     .var 0 is this Ljp/ngt/ngtlib/renderer/model/PolygonModel; from L_0000 to L_0005
     aload 0
     getfield jp/ngt/ngtlib/renderer/model/PolygonModel/sizeBox "[F"
     areturn
 L_0005:
 .end method
 
-.method public renderAll (Z)V
+.method public final renderAll (Z)V
     .limit stack 3
     .limit local 3
 L_0000:
     .line 158
     .var 0 is this Ljp/ngt/ngtlib/renderer/model/PolygonModel; from L_0000 to L_002a
     .var 1 is smoothing Z from L_0000 to L_002a
     iload 1
     ifeq L_0008
 L_0004:
     .line 160
@@ -538,21 +538,21 @@ L_0026:
     .line 172
     .stack
         locals Object jp/ngt/ngtlib/renderer/model/PolygonModel
         locals Integer
         locals Object jp/ngt/ngtlib/renderer/NGTTessellator
     .end stack
     return
 L_002a:
 .end method
 
-.method public tessellateAll (Ljp/ngt/ngtlib/renderer/NGTTessellator;Z)V
+.method public final tessellateAll (Ljp/ngt/ngtlib/renderer/NGTTessellator;Z)V
     .limit stack 3
     .limit local 5
 L_0000:
     .line 176
     .var 0 is this Ljp/ngt/ngtlib/renderer/model/PolygonModel; from L_0000 to L_001c
     .var 1 is tessellator Ljp/ngt/ngtlib/renderer/NGTTessellator; from L_0000 to L_001c
     .var 2 is smoothing Z from L_0000 to L_001c
     aload 0
     getfield jp/ngt/ngtlib/renderer/model/PolygonModel/groupObjects Ljava/util/List;
     invokeinterface java/util/List/iterator ()Ljava/util/Iterator;
@@ -585,21 +585,21 @@ L_0018:
     .line 180
     .stack
         locals Object jp/ngt/ngtlib/renderer/model/PolygonModel
         locals Object jp/ngt/ngtlib/renderer/NGTTessellator
         locals Integer
     .end stack
     return
 L_001c:
 .end method
 
-.method public varargs renderOnly "(Z[Ljava/lang/String;)V"
+.method public final varargs renderOnly "(Z[Ljava/lang/String;)V"
     .limit stack 2
     .limit local 9
 L_0000:
     .line 185
     .var 0 is this Ljp/ngt/ngtlib/renderer/model/PolygonModel; from L_0000 to L_004c
     .var 1 is smoothing Z from L_0000 to L_004c
     .var 2 is groupNames "[Ljava/lang/String;" from L_0000 to L_004c
     iload 1
     ifeq L_0008
 L_0004:
@@ -701,21 +701,21 @@ L_0044:
     sipush 7424
     invokestatic org/lwjgl/opengl/GL11/glShadeModel (I)V
 L_0048:
     .line 205
     .stack use locals
     .end stack
     return
 L_004c:
 .end method
 
-.method public renderPart (ZLjava/lang/String;)V
+.method public final renderPart (ZLjava/lang/String;)V
     .limit stack 2
     .limit local 5
 L_0000:
     .line 210
     .var 0 is this Ljp/ngt/ngtlib/renderer/model/PolygonModel; from L_0000 to L_0036
     .var 1 is smoothing Z from L_0000 to L_0036
     .var 2 is partName Ljava/lang/String; from L_0000 to L_0036
     iload 1
     ifeq L_0008
 L_0004:
@@ -780,33 +780,33 @@ L_002e:
     sipush 7424
     invokestatic org/lwjgl/opengl/GL11/glShadeModel (I)V
 L_0032:
     .line 227
     .stack use locals
     .end stack
     return
 L_0036:
 .end method
 
-.method public getDrawMode ()I
+.method public final getDrawMode ()I
     .limit stack 1
     .limit local 1
 L_0000:
     .line 232
     .var 0 is this Ljp/ngt/ngtlib/renderer/model/PolygonModel; from L_0000 to L_0005
     aload 0
     getfield jp/ngt/ngtlib/renderer/model/PolygonModel/drawMode I
     ireturn
 L_0005:
 .end method
 
-.method public getGroupObjects ()Ljava/util/List;
+.method public final getGroupObjects ()Ljava/util/List;
     .signature "()Ljava/util/List<Ljp/ngt/ngtlib/renderer/model/GroupObject;>;"
     .limit stack 1
     .limit local 1
 L_0000:
     .line 238
     .var 0 is this Ljp/ngt/ngtlib/renderer/model/PolygonModel; from L_0000 to L_0005
     aload 0
     getfield jp/ngt/ngtlib/renderer/model/PolygonModel/groupObjects Ljava/util/List;
     areturn
 L_0005:
diff --git a/mods/ngtlib.deobf.jar.src.processed/jp/ngt/ngtlib/util/PermissionManager.jasm b/src/main/ngtlib/jp/ngt/ngtlib/util/PermissionManager.jasm
index e394adf..1adc650 100644
--- a/mods/ngtlib.deobf.jar.src.processed/jp/ngt/ngtlib/util/PermissionManager.jasm
+++ b/src/main/ngtlib/jp/ngt/ngtlib/util/PermissionManager.jasm
@@ -634,24 +634,46 @@ L_0029:
     .stack use locals
     .end stack
     return
 L_002d:
 .end method
 
 .method public hasPermission (Lnet/minecraft/entity/player/EntityPlayer;Ljava/lang/String;)Z
     .limit stack 5
     .limit local 3
 L_0000:
-    .line 140
     .var 0 is this Ljp/ngt/ngtlib/util/PermissionManager; from L_0000 to L_002c
     .var 1 is player Lnet/minecraft/entity/player/EntityPlayer; from L_0000 to L_002c
     .var 2 is category Ljava/lang/String; from L_0000 to L_002c
+
+    .line 2146
+    getstatic com/anatawa12/fixRtm/asm/config/MainConfig/addNegativePermissionEnabled Z
+    ifeq L_if_has_negative_permit
+    .line 2147
+    aload 0
+    ldc "negative."
+    aload 2
+    invokevirtual java/lang/String/concat (Ljava/lang/String;)Ljava/lang/String;
+    invokevirtual jp/ngt/ngtlib/util/PermissionManager/getPlayerList (Ljava/lang/String;)Ljava/util/List;
+    aload 1
+    invokevirtual net/minecraft/entity/player/EntityPlayer/getName ()Ljava/lang/String;
+    invokeinterface java/util/List/contains (Ljava/lang/Object;)Z
+    ifeq L_if_has_negative_permit
+    goto L_no_permission
+L_if_has_negative_permit:
+    .line 140
+    .stack
+        locals Object jp/ngt/ngtlib/util/PermissionManager
+        locals Object net/minecraft/entity/player/EntityPlayer
+        locals Object java/lang/String
+    .end stack
+
     aload 0
     aload 1
     invokevirtual jp/ngt/ngtlib/util/PermissionManager/isOp (Lnet/minecraft/entity/player/EntityPlayer;)Z
     ifeq L_000a
 L_0006:
     .line 142
     iconst_1
     ireturn
 L_000a:
     .line 146
@@ -665,20 +687,40 @@ L_000a:
     invokevirtual jp/ngt/ngtlib/util/PermissionManager/getPlayerList (Ljava/lang/String;)Ljava/util/List;
     aload 1
     invokevirtual net/minecraft/entity/player/EntityPlayer/getName ()Ljava/lang/String;
     invokeinterface java/util/List/contains (Ljava/lang/Object;)Z
     ifeq L_0018
 L_0014:
     .line 148
     iconst_1
     ireturn
 L_0018:
+
+    .line 1146
+    .stack use locals
+    .end stack
+    getstatic com/anatawa12/fixRtm/asm/config/MainConfig/addAllowAllPermissionEnabled Z
+    ifeq L_if_has_not_all_permit
+    .line 1147
+    aload 0
+    ldc "fixrtm.all_permit"
+    invokevirtual jp/ngt/ngtlib/util/PermissionManager/getPlayerList (Ljava/lang/String;)Ljava/util/List;
+    aload 1
+    invokevirtual net/minecraft/entity/player/EntityPlayer/getName ()Ljava/lang/String;
+    invokeinterface java/util/List/contains (Ljava/lang/Object;)Z
+    ifeq L_if_has_not_all_permit
+    .line 1148
+    iconst_1
+    ireturn
+L_if_has_not_all_permit:
+L_no_permission:
+
     .line 152
     .stack use locals
     .end stack
     ldc "%s need permission (%s)."
     iconst_2
     anewarray java/lang/Object
     dup
     iconst_0
     aload 1
     invokevirtual net/minecraft/entity/player/EntityPlayer/getName ()Ljava/lang/String;
@@ -704,20 +746,32 @@ L_0000:
     .var 1 is player Lnet/minecraft/entity/player/EntityPlayer; from L_0000 to L_003f
     getstatic jp/ngt/ngtlib/util/PermissionManager/DEBUG_MODE Z
     ifne L_000a
     invokestatic jp/ngt/ngtlib/util/NGTUtil/isSMP ()Z
     ifne L_000a
 L_0006:
     .line 162
     iconst_1
     ireturn
 L_000a:
+
+    .line 1164
+    .stack
+        locals Object jp/ngt/ngtlib/util/PermissionManager
+        locals Object net/minecraft/entity/player/EntityPlayer
+    .end stack
+    aload 1
+    ifnonnull L_player_non_null
+    iconst_1
+    ireturn
+L_player_non_null:
+
     .line 164
     .stack
         locals Object jp/ngt/ngtlib/util/PermissionManager
         locals Object net/minecraft/entity/player/EntityPlayer
     .end stack
     aload 1
     instanceof net/minecraft/entity/player/EntityPlayerMP
     ifeq L_003a
 L_0010:
     .line 166
