diff --git a/mods/rtm.deobf.jar.src.processed/jp/ngt/rtm/RTMItem.jasm b/src/main/rtm/jp/ngt/rtm/RTMItem.jasm
index 2297030..17edb7e 100644
--- a/mods/rtm.deobf.jar.src.processed/jp/ngt/rtm/RTMItem.jasm
+++ b/src/main/rtm/jp/ngt/rtm/RTMItem.jasm
@@ -667,21 +667,21 @@ L_0012:
 L_0018:
     .line 153
     getstatic jp/ngt/rtm/RTMItem/itemtrain Lnet/minecraft/item/Item;
     iconst_3
     ldc "item_train_3"
     invokestatic jp/ngt/rtm/RTMItem/registerItemModel (Lnet/minecraft/item/Item;ILjava/lang/String;)V
 L_001e:
     .line 154
     getstatic jp/ngt/rtm/RTMItem/itemtrain Lnet/minecraft/item/Item;
     bipush 127
-    ldc "item_train_127"
+    ldc "item_train_fixrtm_test"
     invokestatic jp/ngt/rtm/RTMItem/registerItemModel (Lnet/minecraft/item/Item;ILjava/lang/String;)V
 L_0024:
     .line 155
     getstatic jp/ngt/rtm/RTMItem/itemMotorman Lnet/minecraft/item/Item;
     iconst_0
     ldc "item_npc_0"
     invokestatic jp/ngt/rtm/RTMItem/registerItemModel (Lnet/minecraft/item/Item;ILjava/lang/String;)V
 L_002a:
     .line 156
     getstatic jp/ngt/rtm/RTMItem/itemMotorman Lnet/minecraft/item/Item;
diff --git a/mods/rtm.deobf.jar.src.processed/jp/ngt/rtm/entity/train/EntityBogie.jasm b/src/main/rtm/jp/ngt/rtm/entity/train/EntityBogie.jasm
index 5ca3be3..aa70ce9 100644
--- a/mods/rtm.deobf.jar.src.processed/jp/ngt/rtm/entity/train/EntityBogie.jasm
+++ b/src/main/rtm/jp/ngt/rtm/entity/train/EntityBogie.jasm
@@ -1547,24 +1547,34 @@ L_0012:
     .end stack
     iconst_0
     istore 1
 L_0017:
     .line 376
     .stack use locals
     .end stack
     aload 0
     invokevirtual jp/ngt/rtm/entity/train/EntityBogie/getTrain ()Ljp/ngt/rtm/entity/train/EntityTrainBase;
     ifnonnull L_0021
+
+    .line 1378
+    aload 0
+    getfield jp/ngt/rtm/entity/train/EntityBogie/world Lnet/minecraft/world/World;
+    getfield net/minecraft/world/World/isRemote Z
+    ifne L_ifRemote
+
 L_001d:
     .line 378
     aload 0
     invokevirtual jp/ngt/rtm/entity/train/EntityBogie/setDead ()V
+
+L_ifRemote:
+
 L_0021:
     .line 380
     .stack use locals
     .end stack
     return
 L_0025:
 .end method
 
 .method public onBogieUpdate ()V
     .limit stack 2
diff --git a/mods/rtm.deobf.jar.src.processed/jp/ngt/rtm/entity/vehicle/EntityVehicleBase.jasm b/src/main/rtm/jp/ngt/rtm/entity/vehicle/EntityVehicleBase.jasm
index b252a06..0c0db45 100644
--- a/mods/rtm.deobf.jar.src.processed/jp/ngt/rtm/entity/vehicle/EntityVehicleBase.jasm
+++ b/src/main/rtm/jp/ngt/rtm/entity/vehicle/EntityVehicleBase.jasm
@@ -1068,48 +1068,50 @@ L_0004:
     astore 4
 L_000b:
     .line 365
     .var 4 is set Ljp/ngt/rtm/modelpack/modelset/ModelSetBase; from L_000b to L_0011
     aload 4
     invokevirtual jp/ngt/rtm/modelpack/modelset/ModelSetBase/getCollisionObj ()Ljp/ngt/rtm/entity/util/CollisionObj;
     invokevirtual jp/ngt/rtm/entity/util/CollisionObj/getSizeBox ()Lnet/minecraft/util/math/AxisAlignedBB;
     astore 3
 L_0011:
     .line 371
-    goto L_0028
+    goto L_end_try
 L_0014:
     .line 367
     .stack
         locals Object jp/ngt/rtm/entity/vehicle/EntityVehicleBase
         locals Object net/minecraft/entity/Entity
         locals Object net/minecraft/entity/Entity
         locals Object net/minecraft/util/math/AxisAlignedBB
         stacks Object java/lang/NullPointerException
     .end stack
-    astore 4
-L_0018:
-    .line 369
-    .var 4 is e Ljava/lang/NullPointerException; from L_0018 to L_0028
-    aload 4
-    invokevirtual java/lang/NullPointerException/printStackTrace ()V
+    pop
+L_end_try:
+    .stack use locals
+    .end stack
+    aload 3
+    invokestatic com/anatawa12/fixRtm/rtm/HooksKt/fixRiderPosOnDismount_remakeAABB (Lnet/minecraft/util/math/AxisAlignedBB;)Z
+    ifeq L_aabb_remake_end
 L_001c:
     .line 370
     new net/minecraft/util/math/AxisAlignedBB
     dup
     ldc -1.5
     dconst_0
     ldc -2.0
     ldc 1.5
     ldc 3.0
     ldc 2.0
     invokespecial net/minecraft/util/math/AxisAlignedBB/<init> (DDDDDD)V
     astore 3
+L_aabb_remake_end:
 L_0028:
     .line 375
     .stack use locals
     .end stack
     aload 2
     getfield net/minecraft/entity/Entity/posX D
     aload 0
     getfield jp/ngt/rtm/entity/vehicle/EntityVehicleBase/posX D
     dsub
     aload 2
@@ -1228,21 +1230,21 @@ L_0092:
     .line 387
     .var 12 is z D from L_0092 to L_00b1
     aload 0
     getfield jp/ngt/rtm/entity/vehicle/EntityVehicleBase/world Lnet/minecraft/world/World;
     new net/minecraft/util/math/BlockPos
     dup
     dload 8
     dload 10
     dload 12
     invokespecial net/minecraft/util/math/BlockPos/<init> (DDD)V
-    invokevirtual net/minecraft/world/World/getTopSolidOrLiquidBlock (Lnet/minecraft/util/math/BlockPos;)Lnet/minecraft/util/math/BlockPos;
+    invokestatic com/anatawa12/fixRtm/rtm/HooksKt/fixRiderPosOnDismount_calcBestBlockPos (Lnet/minecraft/world/World;Lnet/minecraft/util/math/BlockPos;)Lnet/minecraft/util/math/BlockPos;
     astore 14
 L_009e:
     .line 388
     .var 14 is pos Lnet/minecraft/util/math/BlockPos; from L_009e to L_00b1
     aload 1
     aload 14
     invokevirtual net/minecraft/util/math/BlockPos/getX ()I
     i2d
     ldc 0.5
     dadd
diff --git a/mods/rtm.deobf.jar.src.processed/jp/ngt/rtm/entity/vehicle/WeatherEffectDummy.jasm b/src/main/rtm/jp/ngt/rtm/entity/vehicle/WeatherEffectDummy.jasm
index d0e484a..ab9a52f 100644
--- a/mods/rtm.deobf.jar.src.processed/jp/ngt/rtm/entity/vehicle/WeatherEffectDummy.jasm
+++ b/src/main/rtm/jp/ngt/rtm/entity/vehicle/WeatherEffectDummy.jasm
@@ -226,10 +226,21 @@ L_0003:
     .limit stack 0
     .limit local 2
 L_0000:
     .line 85
     .var 0 is this Ljp/ngt/rtm/entity/vehicle/WeatherEffectDummy; from L_0000 to L_0003
     .var 1 is compound Lnet/minecraft/nbt/NBTTagCompound; from L_0000 to L_0003
     return
 L_0003:
 .end method
 
+.method public getEntityBoundingBox ()Lnet/minecraft/util/math/AxisAlignedBB;
+    .limit stack 1
+    .limit local 1
+L_start:
+    .var 0 is this Ljp/ngt/rtm/entity/vehicle/WeatherEffectDummy; from L_start to L_end
+    aload 0
+    getfield jp/ngt/rtm/entity/vehicle/WeatherEffectDummy/parent Ljp/ngt/rtm/entity/vehicle/EntityVehicleBase;
+    invokevirtual net/minecraft/entity/Entity/getEntityBoundingBox ()Lnet/minecraft/util/math/AxisAlignedBB;
+    areturn
+L_end:
+.end method
diff --git a/mods/rtm.deobf.jar.src.processed/jp/ngt/rtm/event/RTMEventHandler.jasm b/src/main/rtm/jp/ngt/rtm/event/RTMEventHandler.jasm
index aefff78..27c3d26 100644
--- a/mods/rtm.deobf.jar.src.processed/jp/ngt/rtm/event/RTMEventHandler.jasm
+++ b/src/main/rtm/jp/ngt/rtm/event/RTMEventHandler.jasm
@@ -10,48 +10,62 @@
     .limit local 1
 L_0000:
     .line 18
     .var 0 is this Ljp/ngt/rtm/event/RTMEventHandler; from L_0000 to L_0005
     aload 0
     invokespecial java/lang/Object/<init> ()V
     return
 L_0005:
 .end method
 
-.method public onPlayerLoggedIn (Lnet/minecraftforge/fml/common/gameevent/PlayerEvent$PlayerLoggedInEvent;)V
+.method public onServerConnectionFromClient (Lnet/minecraftforge/fml/common/network/FMLNetworkEvent$ServerConnectionFromClientEvent;)V
     .annotation visible net/minecraftforge/fml/common/eventhandler/SubscribeEvent
     .end annotation
     .limit stack 2
     .limit local 2
 L_0000:
     .line 26
     .var 0 is this Ljp/ngt/rtm/event/RTMEventHandler; from L_0000 to L_001e
-    .var 1 is event Lnet/minecraftforge/fml/common/gameevent/PlayerEvent$PlayerLoggedInEvent; from L_0000 to L_001e
+    .var 1 is event Lnet/minecraftforge/fml/common/network/FMLNetworkEvent$ServerConnectionFromClientEvent; from L_0000 to L_001e
     invokestatic jp/ngt/ngtlib/util/NGTUtil/isSMP ()Z
     ifne L_0006
     invokestatic jp/ngt/ngtlib/util/NGTUtil/openedLANWorld ()Z
     ifeq L_000e
 L_0006:
     .line 28
     .stack
         locals Object jp/ngt/rtm/event/RTMEventHandler
-        locals Object net/minecraftforge/fml/common/gameevent/PlayerEvent$PlayerLoggedInEvent
+        locals Object net/minecraftforge/fml/common/network/FMLNetworkEvent$ServerConnectionFromClientEvent
     .end stack
     getstatic jp/ngt/rtm/modelpack/ModelPackManager/INSTANCE Ljp/ngt/rtm/modelpack/ModelPackManager;
     aload 1
-    getfield net/minecraftforge/fml/common/gameevent/PlayerEvent$PlayerLoggedInEvent/player Lnet/minecraft/entity/player/EntityPlayer;
-    checkcast net/minecraft/entity/player/EntityPlayerMP
+    invokevirtual net/minecraftforge/fml/common/network/FMLNetworkEvent$ServerConnectionFromClientEvent/getHandler ()Lnet/minecraft/network/INetHandler;
+    checkcast net/minecraft/network/NetHandlerPlayServer
+    getfield net/minecraft/network/NetHandlerPlayServer/player Lnet/minecraft/entity/player/EntityPlayerMP;
     invokevirtual jp/ngt/rtm/modelpack/ModelPackManager/sendModelSetsToClient (Lnet/minecraft/entity/player/EntityPlayerMP;)V
 L_000e:
     .line 30
     .stack use locals
     .end stack
+    return
+L_001e:
+.end method
+
+.method public onPlayerLoggedIn (Lnet/minecraftforge/fml/common/gameevent/PlayerEvent$PlayerLoggedInEvent;)V
+    .annotation visible net/minecraftforge/fml/common/eventhandler/SubscribeEvent
+    .end annotation
+    .limit stack 2
+    .limit local 2
+L_0000:
+    .var 0 is this Ljp/ngt/rtm/event/RTMEventHandler; from L_0000 to L_001e
+    .var 1 is event Lnet/minecraftforge/fml/common/gameevent/PlayerEvent$PlayerLoggedInEvent; from L_0000 to L_001e
+    .line 30
     getstatic jp/ngt/rtm/block/decoration/DecorationStore/INSTANCE Ljp/ngt/rtm/block/decoration/DecorationStore;
     aload 1
     getfield net/minecraftforge/fml/common/gameevent/PlayerEvent$PlayerLoggedInEvent/player Lnet/minecraft/entity/player/EntityPlayer;
     invokevirtual net/minecraft/entity/player/EntityPlayer/getEntityWorld ()Lnet/minecraft/world/World;
     invokevirtual jp/ngt/rtm/block/decoration/DecorationStore/loadModels (Lnet/minecraft/world/World;)V
 L_0016:
     .line 31
     iconst_1
     invokestatic jp/ngt/rtm/sound/SpeakerSounds/getInstance (Z)Ljp/ngt/rtm/sound/SpeakerSounds;
     invokevirtual jp/ngt/rtm/sound/SpeakerSounds/syncSoundList ()V
diff --git a/mods/rtm.deobf.jar.src.processed/jp/ngt/rtm/modelpack/ModelPackManager.jasm b/src/main/rtm/jp/ngt/rtm/modelpack/ModelPackManager.jasm
index 79fab25..489b1a8 100644
--- a/mods/rtm.deobf.jar.src.processed/jp/ngt/rtm/modelpack/ModelPackManager.jasm
+++ b/src/main/rtm/jp/ngt/rtm/modelpack/ModelPackManager.jasm
@@ -12,29 +12,29 @@
 .field private static final SC_INCLUDE Ljava/util/regex/Pattern;
 .end field
 
 .field private static final ENCODING "[Ljava/lang/String;"
 .end field
 
 .field private final typeMap Ljava/util/Map;
     .signature "Ljava/util/Map<Ljava/lang/String;Ljp/ngt/rtm/modelpack/ResourceType;>;"
 .end field
 
-.field private final allModelSetMap Ljava/util/Map;
+.field public final allModelSetMap Ljava/util/Map;
     .signature "Ljava/util/Map<Ljp/ngt/rtm/modelpack/ResourceType;Ljava/util/Map<Ljava/lang/String;Ljp/ngt/rtm/modelpack/modelset/ResourceSet;>;>;"
 .end field
 
 .field private final smpModelSetMap Ljava/util/Map;
     .signature "Ljava/util/Map<Ljp/ngt/rtm/modelpack/ResourceType;Ljava/util/Map<Ljava/lang/String;Ljp/ngt/rtm/modelpack/modelset/ResourceSet;>;>;"
 .end field
 
-.field private final dummyMap Ljava/util/Map;
+.field public final dummyMap Ljava/util/Map;
     .signature "Ljava/util/Map<Ljava/lang/String;Ljp/ngt/rtm/modelpack/modelset/ResourceSet;>;"
 .end field
 
 .field public final unconstructSets Ljava/util/List;
     .signature "Ljava/util/List<Ljp/ngt/rtm/modelpack/modelset/ResourceSet;>;"
 .end field
 
 .field private final modelCache Ljava/util/Map;
     .signature "Ljava/util/Map<Ljava/lang/String;Ljp/ngt/ngtlib/renderer/model/IModelNGT;>;"
 .end field
@@ -956,26 +956,34 @@ L_0048:
 L_004b:
     .line 260
     .stack
         locals Object jp/ngt/rtm/modelpack/ModelPackManager
         locals Object net/minecraft/entity/player/EntityPlayerMP
         locals Integer
         locals Object java/util/Iterator
     .end stack
     goto L_000b
 L_004f:
-    .line 261
+    .line 1261
     .stack
         locals Object jp/ngt/rtm/modelpack/ModelPackManager
         locals Object net/minecraft/entity/player/EntityPlayerMP
         locals Integer
     .end stack
+
+    new com/anatawa12/fixRtm/network/SentAllModels
+    dup
+    invokespecial com/anatawa12/fixRtm/network/SentAllModels/<init> ()V
+    aload 1
+    invokestatic com/anatawa12/fixRtm/network/NetworkHandler/sendPacketEPM (Lnet/minecraftforge/fml/common/network/simpleimpl/IMessage;Lnet/minecraft/entity/player/EntityPlayerMP;)V
+
+    .line 261
     return
 L_0053:
 .end method
 
 .method public addModelSetName (ILjava/lang/String;Ljava/lang/String;)V
     .limit stack 3
     .limit local 6
 L_0000:
     .line 266
     .var 0 is this Ljp/ngt/rtm/modelpack/ModelPackManager; from L_0000 to L_0068
@@ -1190,20 +1198,21 @@ L_002e:
 .method public getResourceSet (Ljp/ngt/rtm/modelpack/ResourceType;Ljava/lang/String;)Ljp/ngt/rtm/modelpack/modelset/ResourceSet;
     .signature "<T:Ljp/ngt/rtm/modelpack/modelset/ResourceSet;>(Ljp/ngt/rtm/modelpack/ResourceType;Ljava/lang/String;)TT;"
     .limit stack 4
     .limit local 7
 L_0000:
     .line 310
     .var 0 is this Ljp/ngt/rtm/modelpack/ModelPackManager; from L_0000 to L_005d
     .var 1 is type Ljp/ngt/rtm/modelpack/ResourceType; from L_0000 to L_005d
     .var 2 is name Ljava/lang/String; from L_0000 to L_005d
     aload 1
+    invokestatic jp/ngt/rtm/modelpack/ModelPackManager/"get parent or me" (Ljp/ngt/rtm/modelpack/ResourceType;)Ljp/ngt/rtm/modelpack/ResourceType;
     astore 3
 L_0004:
     .line 311
     .var 3 is parent Ljp/ngt/rtm/modelpack/ResourceType; from L_0004 to L_005d
     aload 1
     getfield jp/ngt/rtm/modelpack/ResourceType/parent Ljp/ngt/rtm/modelpack/ResourceType;
     ifnull L_000e
 L_0009:
     .line 313
     aload 1
@@ -1266,64 +1275,34 @@ L_002b:
     invokeinterface java/util/Map/get (Ljava/lang/Object;)Ljava/lang/Object;
     checkcast jp/ngt/rtm/modelpack/modelset/ResourceSet
     astore 6
 L_0035:
     .line 319
     .var 6 is modelSet Ljp/ngt/rtm/modelpack/modelset/ResourceSet; signature "TT;" from L_0035 to L_005d
     aload 6
     ifnonnull L_0058
 L_0039:
     .line 321
-    aload 0
-    getfield jp/ngt/rtm/modelpack/ModelPackManager/dummyMap Ljava/util/Map;
-    aload 1
-    getfield jp/ngt/rtm/modelpack/ResourceType/hasSubType Z
-    ifeq L_0043
     aload 1
-    getfield jp/ngt/rtm/modelpack/ResourceType/subType Ljava/lang/String;
-    goto L_0047
-L_0043:
+    aload 2
+    invokestatic com/anatawa12/fixRtm/DummyModelPackManager/getSet (Ljp/ngt/rtm/modelpack/ResourceType;Ljava/lang/String;)Ljp/ngt/rtm/modelpack/modelset/ResourceSet;
+    areturn
+L_0058:
+    .line 327
     .stack
         locals Object jp/ngt/rtm/modelpack/ModelPackManager
         locals Object jp/ngt/rtm/modelpack/ResourceType
         locals Object java/lang/String
         locals Object jp/ngt/rtm/modelpack/ResourceType
         locals Integer
         locals Object java/util/Map
         locals Object jp/ngt/rtm/modelpack/modelset/ResourceSet
-        stacks Object java/util/Map
-    .end stack
-    aload 1
-    getfield jp/ngt/rtm/modelpack/ResourceType/name Ljava/lang/String;
-L_0047:
-    .stack use locals
-        stacks Object java/util/Map
-        stacks Object java/lang/Object
-    .end stack
-    invokeinterface java/util/Map/get (Ljava/lang/Object;)Ljava/lang/Object;
-    checkcast jp/ngt/rtm/modelpack/modelset/ResourceSet
-    astore 6
-L_004c:
-    .line 322
-    aload 6
-    ifnonnull L_0058
-L_0050:
-    .line 324
-    new jp/ngt/rtm/modelpack/ModelPackException
-    dup
-    ldc "Default model is not registered."
-    aload 2
-    invokespecial jp/ngt/rtm/modelpack/ModelPackException/<init> (Ljava/lang/String;Ljava/lang/String;)V
-    athrow
-L_0058:
-    .line 327
-    .stack use locals
     .end stack
     aload 6
     areturn
 L_005d:
 .end method
 
 .method public getModelList (Ljp/ngt/rtm/modelpack/ResourceType;)Ljava/util/List;
     .signature "(Ljp/ngt/rtm/modelpack/ResourceType;)Ljava/util/List<Ljp/ngt/rtm/modelpack/modelset/ResourceSet;>;"
     .limit stack 3
     .limit local 4
@@ -2093,10 +2072,31 @@ L_0018:
     ldc "UTF-8"
     aastore
     dup
     iconst_1
     ldc "SJIS"
     aastore
     putstatic jp/ngt/rtm/modelpack/ModelPackManager/ENCODING "[Ljava/lang/String;"
     return
 .end method
 
+.method public static "get parent or me" "(Ljp/ngt/rtm/modelpack/ResourceType;)Ljp/ngt/rtm/modelpack/ResourceType;"
+    .limit local 1
+    .limit stack 1
+
+    .stack
+        locals Object jp/ngt/rtm/modelpack/ResourceType
+    .end stack
+    aload 0
+    getfield jp/ngt/rtm/modelpack/ResourceType/parent Ljp/ngt/rtm/modelpack/ResourceType;
+    ifnull L_if_null_to
+    .stack use locals
+    .end stack
+    aload 0
+    getfield jp/ngt/rtm/modelpack/ResourceType/parent Ljp/ngt/rtm/modelpack/ResourceType;
+    areturn
+L_if_null_to:
+    .stack use locals
+    .end stack
+    aload 0
+    areturn
+.end method
diff --git a/mods/rtm.deobf.jar.src.processed/jp/ngt/rtm/modelpack/init/ModelPackConstructThread.jasm b/src/main/rtm/jp/ngt/rtm/modelpack/init/ModelPackConstructThread.jasm
index 09bef39..c998070 100644
--- a/mods/rtm.deobf.jar.src.processed/jp/ngt/rtm/modelpack/init/ModelPackConstructThread.jasm
+++ b/src/main/rtm/jp/ngt/rtm/modelpack/init/ModelPackConstructThread.jasm
@@ -1,13 +1,13 @@
 .bytecode 52.0
 .source "ModelPackConstructThread.java"
-.class public final jp/ngt/rtm/modelpack/init/ModelPackConstructThread
+.class public jp/ngt/rtm/modelpack/init/ModelPackConstructThread
 .super java/lang/Thread
 .inner public static final enum jp/ngt/rtm/modelpack/init/ProgressStateHolder$ProgressState inner ProgressState outer jp/ngt/rtm/modelpack/init/ProgressStateHolder
 
 .field private final threadSide Lnet/minecraftforge/fml/relauncher/Side;
 .end field
 
 .field private final parent Ljp/ngt/rtm/modelpack/init/ModelPackLoadThread;
 .end field
 
 .field private loading Z
diff --git a/mods/rtm.deobf.jar.src.processed/jp/ngt/rtm/modelpack/init/ModelPackLoadThread.jasm b/src/main/rtm/jp/ngt/rtm/modelpack/init/ModelPackLoadThread.jasm
index 0a49c17..d210f43 100644
--- a/mods/rtm.deobf.jar.src.processed/jp/ngt/rtm/modelpack/init/ModelPackLoadThread.jasm
+++ b/src/main/rtm/jp/ngt/rtm/modelpack/init/ModelPackLoadThread.jasm
@@ -547,45 +547,45 @@ L_0035:
     iconst_0
     invokestatic jp/ngt/rtm/modelpack/init/ProgressStateHolder$ProgressState/values "()[Ljp/ngt/rtm/modelpack/init/ProgressStateHolder\$ProgressState;"
     arraylength
     ldc ""
     invokevirtual jp/ngt/rtm/modelpack/init/ModelPackLoadThread/setBarMaxValue (IILjava/lang/String;)V
 L_003e:
     .line 184
     invokestatic jp/ngt/ngtlib/io/NGTLog/startTimer ()V
 L_0041:
     .line 185
-    new jp/ngt/rtm/modelpack/init/ModelPackConstructThread
+    new com/anatawa12/fixRtm/rtm/modelpack/init/ExModelPackConstructThread
     dup
     aload 0
     getfield jp/ngt/rtm/modelpack/init/ModelPackLoadThread/threadSide Lnet/minecraftforge/fml/relauncher/Side;
     aload 0
-    invokespecial jp/ngt/rtm/modelpack/init/ModelPackConstructThread/<init> (Lnet/minecraftforge/fml/relauncher/Side;Ljp/ngt/rtm/modelpack/init/ModelPackLoadThread;)V
+    invokespecial com/anatawa12/fixRtm/rtm/modelpack/init/ExModelPackConstructThread/<init> (Lnet/minecraftforge/fml/relauncher/Side;Ljp/ngt/rtm/modelpack/init/ModelPackLoadThread;)V
     astore 1
 L_004a:
     .line 186
-    .var 1 is thread2 Ljp/ngt/rtm/modelpack/init/ModelPackConstructThread; from L_004a to L_006a
+    .var 1 is thread2 Lcom/anatawa12/fixRtm/rtm/modelpack/init/ExModelPackConstructThread; from L_004a to L_006a
     aload 1
-    invokevirtual jp/ngt/rtm/modelpack/init/ModelPackConstructThread/start ()V
+    invokevirtual com/anatawa12/fixRtm/rtm/modelpack/init/ExModelPackConstructThread/start ()V
 L_004e:
     .line 187
     getstatic jp/ngt/rtm/modelpack/ModelPackManager/INSTANCE Ljp/ngt/rtm/modelpack/ModelPackManager;
     aload 0
     invokevirtual jp/ngt/rtm/modelpack/ModelPackManager/load (Ljp/ngt/rtm/modelpack/init/ModelPackLoadThread;)V
 L_0053:
     .line 188
     .stack
         locals Object jp/ngt/rtm/modelpack/init/ModelPackLoadThread
-        locals Object jp/ngt/rtm/modelpack/init/ModelPackConstructThread
+        locals Object com/anatawa12/fixRtm/rtm/modelpack/init/ExModelPackConstructThread
     .end stack
     aload 1
-    invokevirtual jp/ngt/rtm/modelpack/init/ModelPackConstructThread/setFinish ()Z
+    invokevirtual com/anatawa12/fixRtm/rtm/modelpack/init/ExModelPackConstructThread/setFinish ()Z
     ifne L_005e
 L_0059:
     .line 190
     ldc 500L
     invokestatic jp/ngt/rtm/modelpack/init/ModelPackLoadThread/sleep (J)V
     goto L_0053
 L_005e:
     .line 192
     .stack use locals
     .end stack
diff --git a/mods/rtm.deobf.jar.src.processed/jp/ngt/rtm/modelpack/state/ResourceState.jasm b/src/main/rtm/jp/ngt/rtm/modelpack/state/ResourceState.jasm
index 2945cc2..a90bdee 100644
--- a/mods/rtm.deobf.jar.src.processed/jp/ngt/rtm/modelpack/state/ResourceState.jasm
+++ b/src/main/rtm/jp/ngt/rtm/modelpack/state/ResourceState.jasm
@@ -350,20 +350,23 @@ L_0009:
     .stack
         locals Object jp/ngt/rtm/modelpack/state/ResourceState
     .end stack
     aload 0
     getstatic jp/ngt/rtm/modelpack/ModelPackManager/INSTANCE Ljp/ngt/rtm/modelpack/ModelPackManager;
     aload 0
     getfield jp/ngt/rtm/modelpack/state/ResourceState/type Ljp/ngt/rtm/modelpack/ResourceType;
     aload 0
     getfield jp/ngt/rtm/modelpack/state/ResourceState/modelName Ljava/lang/String;
     invokevirtual jp/ngt/rtm/modelpack/ModelPackManager/getResourceSet (Ljp/ngt/rtm/modelpack/ResourceType;Ljava/lang/String;)Ljp/ngt/rtm/modelpack/modelset/ResourceSet;
+    aload 0
+    getfield jp/ngt/rtm/modelpack/state/ResourceState/type Ljp/ngt/rtm/modelpack/ResourceType;
+    invokestatic com/anatawa12/fixRtm/rtm/HooksKt/eraseNullForModelSet (Ljp/ngt/rtm/modelpack/modelset/ResourceSet;Ljp/ngt/rtm/modelpack/ResourceType;)Ljp/ngt/rtm/modelpack/modelset/ResourceSet;
     putfield jp/ngt/rtm/modelpack/state/ResourceState/modelSet Ljp/ngt/rtm/modelpack/modelset/ResourceSet;
 L_0014:
     .line 118
     aload 0
     getfield jp/ngt/rtm/modelpack/state/ResourceState/modelSet Ljp/ngt/rtm/modelpack/modelset/ResourceSet;
     invokevirtual jp/ngt/rtm/modelpack/modelset/ResourceSet/isDummy ()Z
     ifne L_0022
 L_001a:
     .line 120
     aload 0
diff --git a/mods/rtm.deobf.jar.src.processed/jp/ngt/rtm/rail/BlockMarker.jasm b/src/main/rtm/jp/ngt/rtm/rail/BlockMarker.jasm
index d2c0e4b..6ffb4cc 100644
--- a/mods/rtm.deobf.jar.src.processed/jp/ngt/rtm/rail/BlockMarker.jasm
+++ b/src/main/rtm/jp/ngt/rtm/rail/BlockMarker.jasm
@@ -527,20 +527,22 @@ L_000f:
     .limit local 12
 L_0000:
     .line 169
     .var 0 is this Ljp/ngt/rtm/rail/BlockMarker; from L_0000 to L_0052
     .var 1 is world Lnet/minecraft/world/World; from L_0000 to L_0052
     .var 2 is x I from L_0000 to L_0052
     .var 3 is y I from L_0000 to L_0052
     .var 4 is z I from L_0000 to L_0052
     .var 5 is player Lnet/minecraft/entity/player/EntityPlayer; from L_0000 to L_0052
     .var 6 is makeRail Z from L_0000 to L_0052
+    aload 5
+    invokestatic com/anatawa12/fixRtm/rtm/HooksKt/BlockMarker_onMarkerActivated "(Lnet/minecraft/entity/player/EntityPlayer;)V"
     aload 0
     aload 5
     iload 6
     invokevirtual jp/ngt/rtm/rail/BlockMarker/hasRail (Lnet/minecraft/entity/player/EntityPlayer;Z)Ljp/ngt/rtm/modelpack/state/ResourceStateRail;
     astore 7
 L_0007:
     .line 170
     .var 7 is prop Ljp/ngt/rtm/modelpack/state/ResourceStateRail; from L_0007 to L_0052
     aload 7
     ifnull L_004d
diff --git a/mods/rtm.deobf.jar.src.processed/jp/ngt/rtm/rail/RenderMarkerBlock.jasm b/src/main/rtm/jp/ngt/rtm/rail/RenderMarkerBlock.jasm
index 14eaa94..bd54e73 100644
--- a/mods/rtm.deobf.jar.src.processed/jp/ngt/rtm/rail/RenderMarkerBlock.jasm
+++ b/src/main/rtm/jp/ngt/rtm/rail/RenderMarkerBlock.jasm
@@ -963,22 +963,26 @@ L_005c:
     iconst_1
     if_icmpgt L_0098
 L_0061:
     .line 212
     fload 9
     iload 10
     i2f
     fmul
     fstore 11
 L_0068:
-    .line 213
     .var 11 is moveX F from L_0068 to L_0094
+
+    ldc "markerDistanceMoreRealPosition"
+    invokestatic com/anatawa12/fixRtm/asm/Preprocessor/ifDisabled (Ljava/lang/String;)V
+
+    .line 213
     aload 7
     ldc -0.4f
     fload 11
     fadd
     fconst_0
     ldc 0.4f
     fload 9
     fadd
     invokevirtual jp/ngt/ngtlib/renderer/NGTTessellator/addVertex (FFF)V
 L_0073:
@@ -1007,20 +1011,109 @@ L_0089:
     .line 216
     aload 7
     ldc 0.4f
     fload 11
     fadd
     fconst_0
     ldc 0.4f
     fload 9
     fadd
     invokevirtual jp/ngt/ngtlib/renderer/NGTTessellator/addVertex (FFF)V
+
+    ldc "markerDistanceMoreRealPosition"
+    invokestatic com/anatawa12/fixRtm/asm/Preprocessor/ifEnabled (Ljava/lang/String;)V
+
+    .line 1213
+    aload 7
+    ldc -0.4f
+    fload 11
+    fadd
+    fconst_0
+    ldc -0.4f
+    fload 9
+    fadd
+    invokevirtual jp/ngt/ngtlib/renderer/NGTTessellator/addVertex (FFF)V
+    .line 1214
+    aload 7
+    ldc -0.4f
+    fload 11
+    fadd
+    fconst_0
+    ldc -0.6f
+    fload 9
+    fadd
+    invokevirtual jp/ngt/ngtlib/renderer/NGTTessellator/addVertex (FFF)V
+    .line 1215
+    aload 7
+    ldc 0.4f
+    fload 11
+    fadd
+    fconst_0
+    ldc -0.6f
+    fload 9
+    fadd
+    invokevirtual jp/ngt/ngtlib/renderer/NGTTessellator/addVertex (FFF)V
+    .line 1216
+    aload 7
+    ldc 0.4f
+    fload 11
+    fadd
+    fconst_0
+    ldc -0.4f
+    fload 9
+    fadd
+    invokevirtual jp/ngt/ngtlib/renderer/NGTTessellator/addVertex (FFF)V
+
+    .line 1217
+    aload 7
+    ldc -0.1f
+    fload 11
+    fadd
+    fconst_0
+    ldc -0.1f
+    fload 9
+    fadd
+    invokevirtual jp/ngt/ngtlib/renderer/NGTTessellator/addVertex (FFF)V
+    .line 1218
+    aload 7
+    ldc -0.1f
+    fload 11
+    fadd
+    fconst_0
+    ldc -0.9f
+    fload 9
+    fadd
+    invokevirtual jp/ngt/ngtlib/renderer/NGTTessellator/addVertex (FFF)V
+    .line 1219
+    aload 7
+    ldc 0.1f
+    fload 11
+    fadd
+    fconst_0
+    ldc -0.9f
+    fload 9
+    fadd
+    invokevirtual jp/ngt/ngtlib/renderer/NGTTessellator/addVertex (FFF)V
+    .line 1220
+    aload 7
+    ldc 0.1f
+    fload 11
+    fadd
+    fconst_0
+    ldc -0.1f
+    fload 9
+    fadd
+    invokevirtual jp/ngt/ngtlib/renderer/NGTTessellator/addVertex (FFF)V
+
+    ldc ""
+    invokestatic com/anatawa12/fixRtm/asm/Preprocessor/whatever (Ljava/lang/String;)V
+
 L_0094:
     .line 210
     iinc 10 1
     goto L_005c
 L_0098:
     .line 207
     .stack
         locals Object jp/ngt/rtm/rail/RenderMarkerBlock
         locals Object jp/ngt/rtm/rail/TileEntityMarker
         locals Integer
@@ -1124,20 +1217,28 @@ L_00ca:
     fstore 12
 L_00d1:
     .line 229
     .var 12 is moveX F from L_00d1 to L_010a
     invokestatic org/lwjgl/opengl/GL11/glPushMatrix ()V
 L_00d4:
     .line 230
     fload 12
     fconst_0
     fload 10
+
+    ldc "markerDistanceMoreRealPosition"
+    invokestatic com/anatawa12/fixRtm/asm/Preprocessor/ifEnabled (Ljava/lang/String;)V
+    ldc -0.5f
+    fadd
+    ldc ""
+    invokestatic com/anatawa12/fixRtm/asm/Preprocessor/whatever (Ljava/lang/String;)V
+
     invokestatic org/lwjgl/opengl/GL11/glTranslatef (FFF)V
 L_00da:
     .line 231
     invokestatic jp/ngt/ngtlib/util/NGTUtilClient/getMinecraft ()Lnet/minecraft/client/Minecraft;
     invokevirtual net/minecraft/client/Minecraft/getRenderManager ()Lnet/minecraft/client/renderer/entity/RenderManager;
     getfield net/minecraft/client/renderer/entity/RenderManager/playerViewY F
     fneg
     fload 5
     fsub
     fconst_0
diff --git a/mods/rtm.deobf.jar.src.processed/jp/ngt/rtm/rail/util/RailMaker.jasm b/src/main/rtm/jp/ngt/rtm/rail/util/RailMaker.jasm
index 9f15efb..380b0e5 100644
--- a/mods/rtm.deobf.jar.src.processed/jp/ngt/rtm/rail/util/RailMaker.jasm
+++ b/src/main/rtm/jp/ngt/rtm/rail/util/RailMaker.jasm
@@ -509,20 +509,20 @@ L_005a:
     aload 2
     getfield jp/ngt/rtm/rail/util/RailPosition/blockY I
     invokestatic java/lang/Integer/valueOf (I)Ljava/lang/Integer;
     aastore
     dup
     iconst_2
     aload 2
     getfield jp/ngt/rtm/rail/util/RailPosition/blockZ I
     invokestatic java/lang/Integer/valueOf (I)Ljava/lang/Integer;
     aastore
-    invokestatic jp/ngt/ngtlib/io/NGTLog/sendChatMessageToAll "(Ljava/lang/String;[Ljava/lang/Object;)V"
+    invokestatic com/anatawa12/fixRtm/rtm/HooksKt/sendSwitchTypeError "(Ljava/lang/String;[Ljava/lang/Object;)V"
 L_0072:
     .line 101
     .stack use locals
     .end stack
     aconst_null
     areturn
 L_0077:
 .end method
 
diff --git a/mods/rtm.deobf.jar.src.processed/jp/ngt/rtm/rail/util/SwitchType$SwitchSingleCross.jasm b/src/main/rtm/jp/ngt/rtm/rail/util/SwitchType$SwitchSingleCross.jasm
index d1831ec..7eeb299 100644
--- a/mods/rtm.deobf.jar.src.processed/jp/ngt/rtm/rail/util/SwitchType$SwitchSingleCross.jasm
+++ b/src/main/rtm/jp/ngt/rtm/rail/util/SwitchType$SwitchSingleCross.jasm
@@ -290,20 +290,30 @@ L_0089:
     aload 3
     iconst_2
     new jp/ngt/rtm/rail/util/RailMapSwitch
     dup
     aload 4
     aload 5
     aload 6
     aload 7
     invokespecial jp/ngt/rtm/rail/util/RailMapSwitch/<init> (Ljp/ngt/rtm/rail/util/RailPosition;Ljp/ngt/rtm/rail/util/RailPosition;Ljp/ngt/rtm/rail/util/RailDir;Ljp/ngt/rtm/rail/util/RailDir;)V
     aastore
+
+    aload 3
+    invokestatic com/anatawa12/fixRtm/UtilsKt/isAllNotNull ([Ljava/lang/Object;)Z
+    ifne L_all_railMaps_are_not_null
+    iconst_0
+    ireturn
+L_all_railMaps_are_not_null:
+    .stack use locals
+    .end stack
+
 L_0096:
     .line 172
     aload 0
     aload 3
     putfield jp/ngt/rtm/rail/util/SwitchType$SwitchSingleCross/railMaps "[Ljp/ngt/rtm/rail/util/RailMapSwitch;"
 L_009b:
     .line 174
     aload 0
     iconst_4
     anewarray jp/ngt/rtm/rail/util/Point
diff --git a/mods/rtm.deobf.jar.src.processed/jp/ngt/rtm/sound/MovingSoundMaker.jasm b/src/main/rtm/jp/ngt/rtm/sound/MovingSoundMaker.jasm
index 34f470e..019c243 100644
--- a/mods/rtm.deobf.jar.src.processed/jp/ngt/rtm/sound/MovingSoundMaker.jasm
+++ b/src/main/rtm/jp/ngt/rtm/sound/MovingSoundMaker.jasm
@@ -317,20 +317,22 @@ L_0010:
     invokestatic jp/ngt/ngtlib/io/NGTJson/getGson ()Lcom/google/gson/Gson;
     aload 2
     getstatic jp/ngt/rtm/sound/MovingSoundMaker/TYPE Ljava/lang/reflect/ParameterizedType;
     invokevirtual com/google/gson/Gson/fromJson (Ljava/lang/String;Ljava/lang/reflect/Type;)Ljava/lang/Object;
     checkcast java/util/Map
     astore 3
 L_0018:
     .line 115
     .var 3 is map Ljava/util/Map; signature "Ljava/util/Map<Ljava/lang/String;Ljp/ngt/rtm/sound/MovingSoundMaker\$SoundListDummy;>;" from L_0018 to L_009c
     aload 3
+    aload 0
+    invokestatic com/anatawa12/fixRtm/rtm/HooksKt/MovingSoundMaker_loadSoundJson_nullCheck (Ljava/util/Map;Ljava/lang/String;)Ljava/util/Map;
     invokeinterface java/util/Map/entrySet ()Ljava/util/Set;
     invokeinterface java/util/Set/iterator ()Ljava/util/Iterator;
     astore 4
 L_001e:
     .stack
         locals Object java/lang/String
         locals Object java/util/Map
         locals Object java/lang/String
         locals Object java/util/Map
         locals Object java/util/Iterator
